{
  "date": "2026-05-04",
  "arrivals": {
    "count": 85,
    "pax": 15194,
    "countries": {
      "India": {
        "flights": 13,
        "pax": 1911
      },
      "UAE": {
        "flights": 11,
        "pax": 2247
      },
      "Qatar": {
        "flights": 3,
        "pax": 972
      },
      "China": {
        "flights": 13,
        "pax": 1911
      },
      "Oman": {
        "flights": 2,
        "pax": 294
      },
      "Singapore": {
        "flights": 8,
        "pax": 1176
      },
      "Москва": {
        "flights": 1,
        "pax": 324,
        "country": "Russia"
      },
      "Kazakhstan": {
        "flights": 1,
        "pax": 147
      },
      "Malaysia": {
        "flights": 12,
        "pax": 1976
      },
      "Switzerland": {
        "flights": 4,
        "pax": 707
      },
      "Hong Kong": {
        "flights": 5,
        "pax": 857
      },
      "Санкт-Петербург": {
        "flights": 1,
        "pax": 262,
        "country": "Russia"
      },
      "Vietnam": {
        "flights": 3,
        "pax": 589
      },
      "Хабаровск": {
        "flights": 1,
        "pax": 324,
        "country": "Russia"
      },
      "Turkey": {
        "flights": 1,
        "pax": 262
      },
      "Indonesia": {
        "flights": 1,
        "pax": 147
      },
      "Australia": {
        "flights": 2,
        "pax": 352
      },
      "South Korea": {
        "flights": 2,
        "pax": 499
      },
      "Saudi Arabia": {
        "flights": 1,
        "pax": 237
      }
    }
  },
  "departures": {
    "count": 80,
    "pax": 14549,
    "countries": {
      "China": {
        "flights": 13,
        "pax": 1911
      },
      "India": {
        "flights": 12,
        "pax": 1764
      },
      "UAE": {
        "flights": 10,
        "pax": 2190
      },
      "Oman": {
        "flights": 2,
        "pax": 294
      },
      "Qatar": {
        "flights": 3,
        "pax": 972
      },
      "Singapore": {
        "flights": 8,
        "pax": 1176
      },
      "Malaysia": {
        "flights": 12,
        "pax": 1976
      },
      "Kazakhstan": {
        "flights": 1,
        "pax": 147
      },
      "Москва": {
        "flights": 1,
        "pax": 324,
        "country": "Russia"
      },
      "Hong Kong": {
        "flights": 5,
        "pax": 857
      },
      "Switzerland": {
        "flights": 1,
        "pax": 266
      },
      "Vietnam": {
        "flights": 2,
        "pax": 327
      },
      "Екатеринбург": {
        "flights": 1,
        "pax": 262,
        "country": "Russia"
      },
      "Красноярск": {
        "flights": 1,
        "pax": 324,
        "country": "Russia"
      },
      "Indonesia": {
        "flights": 1,
        "pax": 147
      },
      "Новосибирск": {
        "flights": 1,
        "pax": 262,
        "country": "Russia"
      },
      "Australia": {
        "flights": 2,
        "pax": 352
      },
      "Turkey": {
        "flights": 1,
        "pax": 262
      },
      "South Korea": {
        "flights": 2,
        "pax": 499
      },
      "Saudi Arabia": {
        "flights": 1,
        "pax": 237
      }
    }
  },
  "arrivals_list": [
    {
      "fn": "AI 2378",
      "airline": "AIR INDIA LTD",
      "status": "landed",
      "pax": 147,
      "aircraft": "",
      "dep_time": "2026-05-03T18:25",
      "arr_time": "2026-05-04T00:25",
      "from": "DEL",
      "country": "India"
    },
    {
      "fn": "EY 410",
      "airline": "ETIHAD AIRWAYS",
      "status": "landed",
      "pax": 147,
      "aircraft": "",
      "dep_time": "2026-05-04T14:00",
      "arr_time": "2026-05-04T00:35",
      "from": "AUH",
      "country": "UAE"
    },
    {
      "fn": "QR 842",
      "airline": "QATAR AIRWAYS COMPANY",
      "status": "cancelled",
      "pax": 324,
      "aircraft": "77W",
      "dep_time": "2026-05-04T13:20",
      "arr_time": "2026-05-04T00:45",
      "from": "DOH",
      "country": "Qatar"
    },
    {
      "fn": "EY 414",
      "airline": "ETIHAD AIRWAYS",
      "status": "landed",
      "pax": 147,
      "aircraft": "",
      "dep_time": "",
      "arr_time": "2026-05-04T00:45",
      "from": "AUH",
      "country": "UAE"
    },
    {
      "fn": "G9 687",
      "airline": "AIR ARABIA",
      "status": "cancelled",
      "pax": 180,
      "aircraft": "321",
      "dep_time": "2026-05-03T15:50",
      "arr_time": "2026-05-04T00:50",
      "from": "SHJ",
      "country": "UAE"
    },
    {
      "fn": "9C 8667",
      "airline": "SPRING AIRLINES LIMITED CORPORATION",
      "status": "cancelled",
      "pax": 147,
      "aircraft": "320",
      "dep_time": "",
      "arr_time": "2026-05-04T01:00",
      "from": "PVG",
      "country": "China"
    },
    {
      "fn": "WY 833",
      "airline": "OMAN AIR",
      "status": "landed",
      "pax": 147,
      "aircraft": "7M8",
      "dep_time": "",
      "arr_time": "2026-05-04T01:00",
      "from": "MCT",
      "country": "Oman"
    },
    {
      "fn": "9C 8781",
      "airline": "SPRING AIRLINES LIMITED CORPORATION",
      "status": "landed",
      "pax": 147,
      "aircraft": "320",
      "dep_time": "2026-05-04T05:25",
      "arr_time": "2026-05-04T01:05",
      "from": "SZX",
      "country": "China"
    },
    {
      "fn": "FD 197",
      "airline": "THAI AIR ASIA CO.LTD.",
      "status": "cancelled",
      "pax": 147,
      "aircraft": "320",
      "dep_time": "",
      "arr_time": "2026-05-04T01:05",
      "from": "COK",
      "country": "India"
    },
    {
      "fn": "EK 390",
      "airline": "EMIRATES",
      "status": "cancelled",
      "pax": 324,
      "aircraft": "77W",
      "dep_time": "",
      "arr_time": "2026-05-04T01:10",
      "from": "DXB",
      "country": "UAE"
    },
    {
      "fn": "TR 658",
      "airline": "SCOOT PTE LTD",
      "status": "landed",
      "pax": 147,
      "aircraft": "",
      "dep_time": "",
      "arr_time": "2026-05-04T01:20",
      "from": "SIN",
      "country": "Singapore"
    },
    {
      "fn": "SU 284",
      "airline": "AEROFLOT RUSSIAN AIRLINES",
      "status": "landed",
      "pax": 324,
      "aircraft": "77W",
      "dep_time": "2026-05-03T12:10",
      "arr_time": "2026-05-04T01:30",
      "from": "SVO",
      "country": "Russia"
    },
    {
      "fn": "VZ 763",
      "airline": "THAI VIET JET AIR JOINTSTOCK",
      "status": "landed",
      "pax": 147,
      "aircraft": "320",
      "dep_time": "2026-05-04T02:20",
      "arr_time": "2026-05-04T01:30",
      "from": "BOM",
      "country": "India"
    },
    {
      "fn": "SQ 726",
      "airline": "SINGAPORE AIRLINES LIMITED",
      "status": "landed",
      "pax": 147,
      "aircraft": "7M8",
      "dep_time": "2026-05-04T01:20",
      "arr_time": "2026-05-04T01:35",
      "from": "SIN",
      "country": "Singapore"
    },
    {
      "fn": "KC 563",
      "airline": "AIR ASTANA",
      "status": "landed",
      "pax": 147,
      "aircraft": "",
      "dep_time": "2026-05-03T17:30",
      "arr_time": "2026-05-04T02:15",
      "from": "ALA",
      "country": "Kazakhstan"
    },
    {
      "fn": "MH 786",
      "airline": "MALAYSIA AIRLINES",
      "status": "landed",
      "pax": 154,
      "aircraft": "738",
      "dep_time": "",
      "arr_time": "2026-05-04T02:45",
      "from": "KUL",
      "country": "Malaysia"
    },
    {
      "fn": "WK 050",
      "airline": "EDELWEISS AIR AG",
      "status": "landed",
      "pax": 266,
      "aircraft": "359",
      "dep_time": "2026-05-03T12:10",
      "arr_time": "2026-05-04T02:50",
      "from": "ZRH",
      "country": "Switzerland"
    },
    {
      "fn": "G9 699",
      "airline": "AIR ARABIA",
      "status": "cancelled",
      "pax": 180,
      "aircraft": "321",
      "dep_time": "",
      "arr_time": "2026-05-04T02:55",
      "from": "SHJ",
      "country": "UAE"
    },
    {
      "fn": "6E 1071",
      "airline": "INTERGLOBE AVIATION LIMITED (INDIGO)",
      "status": "",
      "pax": 147,
      "aircraft": "",
      "dep_time": "2026-05-02T20:55",
      "arr_time": "2026-05-04T03:05",
      "from": "BOM",
      "country": "India"
    },
    {
      "fn": "UO 724",
      "airline": "HONG KONG EXPRESS AIRWAYS",
      "status": "landed",
      "pax": 147,
      "aircraft": "",
      "dep_time": "",
      "arr_time": "2026-05-04T03:30",
      "from": "HKG",
      "country": "Hong Kong"
    },
    {
      "fn": "SU 628",
      "airline": "AEROFLOT RUSSIAN AIRLINES",
      "status": "confirmed",
      "pax": 262,
      "aircraft": "333",
      "dep_time": "",
      "arr_time": "2026-05-04T03:35",
      "from": "LED",
      "country": "Russia"
    },
    {
      "fn": "AK 832",
      "airline": "AIRASIA BERHAD",
      "status": "landed",
      "pax": 147,
      "aircraft": "320",
      "dep_time": "",
      "arr_time": "2026-05-04T03:40",
      "from": "KUL",
      "country": "Malaysia"
    },
    {
      "fn": "SQ 728",
      "airline": "SINGAPORE AIRLINES LIMITED",
      "status": "landed",
      "pax": 147,
      "aircraft": "7M8",
      "dep_time": "2026-05-04T02:05",
      "arr_time": "2026-05-04T03:50",
      "from": "SIN",
      "country": "Singapore"
    },
    {
      "fn": "CX 771",
      "airline": "CATHAY PACIFIC AIRWAYS",
      "status": "landed",
      "pax": 147,
      "aircraft": "",
      "dep_time": "",
      "arr_time": "2026-05-04T03:50",
      "from": "HKG",
      "country": "Hong Kong"
    },
    {
      "fn": "VJ 809",
      "airline": "VIETJET AIR",
      "status": "landed",
      "pax": 147,
      "aircraft": "320",
      "dep_time": "",
      "arr_time": "2026-05-04T03:55",
      "from": "SGN",
      "country": "Vietnam"
    },
    {
      "fn": "6E 1073",
      "airline": "INTERGLOBE AVIATION LIMITED (INDIGO)",
      "status": "landed",
      "pax": 147,
      "aircraft": "",
      "dep_time": "",
      "arr_time": "2026-05-04T04:20",
      "from": "DEL",
      "country": "India"
    },
    {
      "fn": "6E 1087",
      "airline": "INTERGLOBE AVIATION LIMITED (INDIGO)",
      "status": "landed",
      "pax": 147,
      "aircraft": "",
      "dep_time": "",
      "arr_time": "2026-05-04T04:20",
      "from": "CCU",
      "country": "India"
    },
    {
      "fn": "SU 643",
      "airline": "AEROFLOT RUSSIAN AIRLINES",
      "status": "landed",
      "pax": 324,
      "aircraft": "77W",
      "dep_time": "",
      "arr_time": "2026-05-04T04:25",
      "from": "KHV",
      "country": "Russia"
    },
    {
      "fn": "6E 1077",
      "airline": "INTERGLOBE AVIATION LIMITED (INDIGO)",
      "status": "landed",
      "pax": 147,
      "aircraft": "",
      "dep_time": "",
      "arr_time": "2026-05-04T04:45",
      "from": "BLR",
      "country": "India"
    },
    {
      "fn": "TR 656",
      "airline": "SCOOT PTE LTD",
      "status": "landed",
      "pax": 147,
      "aircraft": "",
      "dep_time": "",
      "arr_time": "2026-05-04T04:55",
      "from": "SIN",
      "country": "Singapore"
    },
    {
      "fn": "EK 378",
      "airline": "EMIRATES",
      "status": "landed",
      "pax": 324,
      "aircraft": "77W",
      "dep_time": "2026-05-03T20:00",
      "arr_time": "2026-05-04T05:00",
      "from": "DXB",
      "country": "UAE"
    },
    {
      "fn": "9C 8669",
      "airline": "SPRING AIRLINES LIMITED CORPORATION",
      "status": "cancelled",
      "pax": 147,
      "aircraft": "320",
      "dep_time": "",
      "arr_time": "2026-05-04T05:10",
      "from": "PVG",
      "country": "China"
    },
    {
      "fn": "OD 540",
      "airline": "MALINDO AIRWAYS SDN BHD",
      "status": "landed",
      "pax": 154,
      "aircraft": "738",
      "dep_time": "",
      "arr_time": "2026-05-04T05:30",
      "from": "KUL",
      "country": "Malaysia"
    },
    {
      "fn": "QP 618",
      "airline": "AKASA AIR",
      "status": "landed",
      "pax": 147,
      "aircraft": "7M8",
      "dep_time": "",
      "arr_time": "2026-05-04T05:40",
      "from": "BOM",
      "country": "India"
    },
    {
      "fn": "CA 413",
      "airline": "AIR CHINA",
      "status": "landed",
      "pax": 147,
      "aircraft": "",
      "dep_time": "",
      "arr_time": "2026-05-04T05:50",
      "from": "TFU",
      "country": ""
    },
    {
      "fn": "AK 824",
      "airline": "AIRASIA BERHAD",
      "status": "confirmed",
      "pax": 147,
      "aircraft": "320",
      "dep_time": "",
      "arr_time": "2026-05-04T06:00",
      "from": "KUL",
      "country": "Malaysia"
    },
    {
      "fn": "MH 794",
      "airline": "MALAYSIA AIRLINES",
      "status": "confirmed",
      "pax": 154,
      "aircraft": "738",
      "dep_time": "2026-05-04T08:20",
      "arr_time": "2026-05-04T06:20",
      "from": "KUL",
      "country": "Malaysia"
    },
    {
      "fn": "FY 3600",
      "airline": "FLYFIREFLY SDN BHD",
      "status": "confirmed",
      "pax": 154,
      "aircraft": "738",
      "dep_time": "",
      "arr_time": "2026-05-04T06:55",
      "from": "PEN",
      "country": "Malaysia"
    },
    {
      "fn": "SQ 732",
      "airline": "SINGAPORE AIRLINES LIMITED",
      "status": "confirmed",
      "pax": 147,
      "aircraft": "7M8",
      "dep_time": "",
      "arr_time": "2026-05-04T07:10",
      "from": "SIN",
      "country": "Singapore"
    },
    {
      "fn": "AK 1820",
      "airline": "AIRASIA BERHAD",
      "status": "confirmed",
      "pax": 147,
      "aircraft": "320",
      "dep_time": "",
      "arr_time": "2026-05-04T07:15",
      "from": "PEN",
      "country": "Malaysia"
    },
    {
      "fn": "QR 840",
      "airline": "QATAR AIRWAYS COMPANY",
      "status": "landed",
      "pax": 324,
      "aircraft": "77W",
      "dep_time": "",
      "arr_time": "2026-05-04T07:15",
      "from": "DOH",
      "country": "Qatar"
    },
    {
      "fn": "9C 8757",
      "airline": "SPRING AIRLINES LIMITED CORPORATION",
      "status": "cancelled",
      "pax": 147,
      "aircraft": "320",
      "dep_time": "",
      "arr_time": "2026-05-04T07:35",
      "from": "TFU",
      "country": ""
    },
    {
      "fn": "WK50",
      "airline": "Edelweiss Air",
      "from": "ZRH",
      "country": "Switzerland",
      "status": "landed",
      "pax": 147,
      "dep_time": "2026-05-03T18:00",
      "arr_time": "2026-05-04T09:50"
    },
    {
      "fn": "LX8050",
      "airline": null,
      "from": "ZRH",
      "country": "Switzerland",
      "status": "landed",
      "pax": 147,
      "dep_time": "2026-05-03T18:00",
      "arr_time": "2026-05-04T09:50"
    },
    {
      "fn": "LH4524",
      "airline": null,
      "from": "ZRH",
      "country": "Switzerland",
      "status": "landed",
      "pax": 147,
      "dep_time": "2026-05-03T18:00",
      "arr_time": "2026-05-04T09:50"
    },
    {
      "fn": "QP 623",
      "airline": "AKASA AIR",
      "status": "confirmed",
      "pax": 147,
      "aircraft": "7M8",
      "dep_time": "2026-05-04T03:00",
      "arr_time": "2026-05-04T08:05",
      "from": "BLR",
      "country": "India"
    },
    {
      "fn": "TK 172",
      "airline": "TURK HAVA YOLLARI (TURKISH AIRLINES CO.)",
      "status": "confirmed",
      "pax": 262,
      "aircraft": "333",
      "dep_time": "",
      "arr_time": "2026-05-04T08:20",
      "from": "IST",
      "country": "Turkey"
    },
    {
      "fn": "AK 822",
      "airline": "AIRASIA BERHAD",
      "status": "",
      "pax": 147,
      "aircraft": "320",
      "dep_time": "",
      "arr_time": "2026-05-04T08:30",
      "from": "KUL",
      "country": "Malaysia"
    },
    {
      "fn": "CZ 6063",
      "airline": "CHINA SOUTHERN AIRLINES",
      "status": "confirmed",
      "pax": 147,
      "aircraft": "320",
      "dep_time": "2026-05-04T06:40",
      "arr_time": "2026-05-04T08:40",
      "from": "CAN",
      "country": "China"
    },
    {
      "fn": "IX 938",
      "airline": "AIR INDIA EXPRESS",
      "status": "confirmed",
      "pax": 147,
      "aircraft": "7M8",
      "dep_time": "",
      "arr_time": "2026-05-04T08:50",
      "from": "HYD",
      "country": "India"
    },
    {
      "fn": "AK 820",
      "airline": "AIRASIA BERHAD",
      "status": "",
      "pax": 147,
      "aircraft": "320",
      "dep_time": "",
      "arr_time": "2026-05-04T09:35",
      "from": "KUL",
      "country": "Malaysia"
    },
    {
      "fn": "AK 1316",
      "airline": "AIRASIA BERHAD",
      "status": "cancelled",
      "pax": 147,
      "aircraft": "320",
      "dep_time": "",
      "arr_time": "2026-05-04T09:45",
      "from": "JHB",
      "country": ""
    },
    {
      "fn": "SQ 736",
      "airline": "SINGAPORE AIRLINES LIMITED",
      "status": "",
      "pax": 147,
      "aircraft": "7M8",
      "dep_time": "",
      "arr_time": "2026-05-04T10:10",
      "from": "SIN",
      "country": "Singapore"
    },
    {
      "fn": "CX 773",
      "airline": "CATHAY PACIFIC AIRWAYS",
      "status": "",
      "pax": 262,
      "aircraft": "333",
      "dep_time": "",
      "arr_time": "2026-05-04T10:20",
      "from": "HKG",
      "country": "Hong Kong"
    },
    {
      "fn": "MH 790",
      "airline": "MALAYSIA AIRLINES",
      "status": "",
      "pax": 154,
      "aircraft": "738",
      "dep_time": "2026-05-04T10:05",
      "arr_time": "2026-05-04T10:25",
      "from": "KUL",
      "country": "Malaysia"
    },
    {
      "fn": "G9 714",
      "airline": "AIR ARABIA",
      "status": "",
      "pax": 180,
      "aircraft": "321",
      "dep_time": "",
      "arr_time": "2026-05-04T10:40",
      "from": "SHJ",
      "country": "UAE"
    },
    {
      "fn": "CA 821",
      "airline": "AIR CHINA",
      "status": "confirmed",
      "pax": 147,
      "aircraft": "7M8",
      "dep_time": "",
      "arr_time": "2026-05-04T10:45",
      "from": "PEK",
      "country": "China"
    },
    {
      "fn": "VN 621",
      "airline": "VIETNAM AIRLINES",
      "status": "cancelled",
      "pax": 180,
      "aircraft": "321",
      "dep_time": "",
      "arr_time": "2026-05-04T10:50",
      "from": "SGN",
      "country": "Vietnam"
    },
    {
      "fn": "3U 3931",
      "airline": "SICHUAN AIRLINES",
      "status": "",
      "pax": 180,
      "aircraft": "321",
      "dep_time": "2026-05-04T07:45",
      "arr_time": "2026-05-04T11:00",
      "from": "TFU",
      "country": ""
    },
    {
      "fn": "EY 412",
      "airline": "ETIHAD AIRWAYS",
      "status": "confirmed",
      "pax": 147,
      "aircraft": "",
      "dep_time": "",
      "arr_time": "2026-05-04T11:20",
      "from": "AUH",
      "country": "UAE"
    },
    {
      "fn": "N4 9907",
      "airline": "NORDWIND AIRLINES",
      "status": "",
      "pax": 262,
      "aircraft": "333",
      "dep_time": "",
      "arr_time": "2026-05-04T11:30",
      "from": "CXR",
      "country": "Vietnam"
    },
    {
      "fn": "HX 741",
      "airline": "HONG KONG AIRLINES LTD",
      "status": "",
      "pax": 147,
      "aircraft": "320",
      "dep_time": "",
      "arr_time": "2026-05-04T11:35",
      "from": "HKG",
      "country": "Hong Kong"
    },
    {
      "fn": "QR 846",
      "airline": "QATAR AIRWAYS COMPANY",
      "status": "cancelled",
      "pax": 324,
      "aircraft": "77W",
      "dep_time": "",
      "arr_time": "2026-05-04T11:50",
      "from": "DOH",
      "country": "Qatar"
    },
    {
      "fn": "QR 841",
      "airline": "QATAR AIRWAYS COMPANY",
      "status": "cancelled",
      "pax": 324,
      "aircraft": "77W",
      "dep_time": "",
      "arr_time": "2026-05-04T12:00",
      "from": "PEN",
      "country": "Malaysia"
    },
    {
      "fn": "QZ 246",
      "airline": "INDONESIA AIRASIA PT.",
      "status": "",
      "pax": 147,
      "aircraft": "320",
      "dep_time": "",
      "arr_time": "2026-05-04T12:10",
      "from": "DPS",
      "country": "Indonesia"
    },
    {
      "fn": "SQ 740",
      "airline": "SINGAPORE AIRLINES LIMITED",
      "status": "",
      "pax": 147,
      "aircraft": "7M8",
      "dep_time": "",
      "arr_time": "2026-05-04T12:15",
      "from": "SIN",
      "country": "Singapore"
    },
    {
      "fn": "EY 416",
      "airline": "ETIHAD AIRWAYS",
      "status": "confirmed",
      "pax": 147,
      "aircraft": "",
      "dep_time": "2026-05-03T19:20",
      "arr_time": "2026-05-04T12:20",
      "from": "AUH",
      "country": "UAE"
    },
    {
      "fn": "JQ 027",
      "airline": "JETSTAR AIRWAYS PTY LIMITED",
      "status": "confirmed",
      "pax": 205,
      "aircraft": "788",
      "dep_time": "2026-05-04T06:05",
      "arr_time": "2026-05-04T12:20",
      "from": "SYD",
      "country": "Australia"
    },
    {
      "fn": "9C 8771",
      "airline": "SPRING AIRLINES LIMITED CORPORATION",
      "status": "cancelled",
      "pax": 147,
      "aircraft": "320",
      "dep_time": "",
      "arr_time": "2026-05-04T12:45",
      "from": "CAN",
      "country": "China"
    },
    {
      "fn": "AI 2376",
      "airline": "AIR INDIA LTD",
      "status": "",
      "pax": 147,
      "aircraft": "",
      "dep_time": "",
      "arr_time": "2026-05-04T12:45",
      "from": "DEL",
      "country": "India"
    },
    {
      "fn": "TR 652",
      "airline": "SCOOT PTE LTD",
      "status": "",
      "pax": 147,
      "aircraft": "",
      "dep_time": "",
      "arr_time": "2026-05-04T12:50",
      "from": "SIN",
      "country": "Singapore"
    },
    {
      "fn": "WY 831",
      "airline": "OMAN AIR",
      "status": "",
      "pax": 147,
      "aircraft": "7M8",
      "dep_time": "",
      "arr_time": "2026-05-04T12:50",
      "from": "MCT",
      "country": "Oman"
    },
    {
      "fn": "EK 396",
      "airline": "EMIRATES",
      "status": "confirmed",
      "pax": 324,
      "aircraft": "77W",
      "dep_time": "2026-05-04T03:35",
      "arr_time": "2026-05-04T13:00",
      "from": "DXB",
      "country": "UAE"
    },
    {
      "fn": "OD 542",
      "airline": "MALINDO AIRWAYS SDN BHD",
      "status": "cancelled",
      "pax": 147,
      "aircraft": "7M8",
      "dep_time": "",
      "arr_time": "2026-05-04T13:15",
      "from": "KUL",
      "country": "Malaysia"
    },
    {
      "fn": "9C 8665",
      "airline": "SPRING AIRLINES LIMITED CORPORATION",
      "status": "",
      "pax": 147,
      "aircraft": "320",
      "dep_time": "",
      "arr_time": "2026-05-04T13:25",
      "from": "PVG",
      "country": "China"
    },
    {
      "fn": "9C 8773",
      "airline": "SPRING AIRLINES LIMITED CORPORATION",
      "status": "",
      "pax": 147,
      "aircraft": "320",
      "dep_time": "",
      "arr_time": "2026-05-04T13:45",
      "from": "CAN",
      "country": "China"
    },
    {
      "fn": "CA 551",
      "airline": "AIR CHINA",
      "status": "",
      "pax": 147,
      "aircraft": "7M8",
      "dep_time": "",
      "arr_time": "2026-05-04T14:00",
      "from": "PEK",
      "country": "China"
    },
    {
      "fn": "JQ 069",
      "airline": "JETSTAR AIRWAYS PTY LIMITED",
      "status": "cancelled",
      "pax": 147,
      "aircraft": "",
      "dep_time": "",
      "arr_time": "2026-05-04T14:30",
      "from": "PER",
      "country": "Australia"
    },
    {
      "fn": "OZ 747",
      "airline": "ASIANA AIRLINES",
      "status": "",
      "pax": 262,
      "aircraft": "333",
      "dep_time": "",
      "arr_time": "2026-05-04T14:40",
      "from": "ICN",
      "country": "South Korea"
    },
    {
      "fn": "6E 1081",
      "airline": "INTERGLOBE AVIATION LIMITED (INDIGO)",
      "status": "",
      "pax": 147,
      "aircraft": "",
      "dep_time": "",
      "arr_time": "2026-05-04T14:50",
      "from": "DEL",
      "country": "India"
    },
    {
      "fn": "6E 1089",
      "airline": "INTERGLOBE AVIATION LIMITED (INDIGO)",
      "status": "",
      "pax": 147,
      "aircraft": "",
      "dep_time": "2026-05-04T08:50",
      "arr_time": "2026-05-04T14:55",
      "from": "BOM",
      "country": "India"
    },
    {
      "fn": "FM 857",
      "airline": "SHANGHAI AIRLINES",
      "status": "",
      "pax": 147,
      "aircraft": "7M8",
      "dep_time": "",
      "arr_time": "2026-05-04T15:00",
      "from": "PVG",
      "country": "China"
    },
    {
      "fn": "KE 677",
      "airline": "KOREAN AIRLINES CO.LTD.",
      "status": "",
      "pax": 237,
      "aircraft": "789",
      "dep_time": "2026-05-04T10:25",
      "arr_time": "2026-05-04T15:10",
      "from": "ICN",
      "country": "South Korea"
    },
    {
      "fn": "HB 270",
      "airline": "GREATER BAY AIRLINES",
      "status": "",
      "pax": 154,
      "aircraft": "738",
      "dep_time": "",
      "arr_time": "2026-05-04T15:10",
      "from": "HKG",
      "country": "Hong Kong"
    },
    {
      "fn": "9C 7653",
      "airline": "SPRING AIRLINES LIMITED CORPORATION",
      "status": "",
      "pax": 147,
      "aircraft": "320",
      "dep_time": "",
      "arr_time": "2026-05-04T15:20",
      "from": "TFU",
      "country": ""
    },
    {
      "fn": "CZ 6057",
      "airline": "CHINA SOUTHERN AIRLINES",
      "status": "",
      "pax": 147,
      "aircraft": "",
      "dep_time": "2026-05-04T12:45",
      "arr_time": "2026-05-04T15:30",
      "from": "CAN",
      "country": "China"
    },
    {
      "fn": "SV 852",
      "airline": "SAUDI ARABIAN AIRLINES",
      "status": "cancelled",
      "pax": 237,
      "aircraft": "789",
      "dep_time": "",
      "arr_time": "2026-05-04T15:30",
      "from": "RUH",
      "country": "Saudi Arabia"
    },
    {
      "fn": "9C 8521",
      "airline": "SPRING AIRLINES LIMITED CORPORATION",
      "status": "",
      "pax": 147,
      "aircraft": "320",
      "dep_time": "",
      "arr_time": "2026-05-04T15:40",
      "from": "PVG",
      "country": "China"
    },
    {
      "fn": "FM 831",
      "airline": "SHANGHAI AIRLINES",
      "status": "",
      "pax": 147,
      "aircraft": "7M8",
      "dep_time": "",
      "arr_time": "2026-05-04T15:45",
      "from": "PVG",
      "country": "China"
    },
    {
      "fn": "DE5917",
      "airline": null,
      "from": "DXB",
      "country": "UAE",
      "status": "landed",
      "pax": 147,
      "dep_time": "2026-05-04T02:35",
      "arr_time": "2026-05-04T12:00"
    }
  ],
  "departures_list": [
    {
      "fn": "FM832",
      "airline": "Shanghai Airlines",
      "to": "PVG",
      "country": "China",
      "status": "active",
      "pax": 147,
      "dep_time": "2026-05-04T00:05",
      "arr_time": "2026-05-04T06:30"
    },
    {
      "fn": "AI 2379",
      "airline": "AIR INDIA LTD",
      "status": "",
      "pax": 147,
      "aircraft": "",
      "dep_time": "2026-05-04T01:25",
      "arr_time": "2026-05-04T04:50",
      "to": "DEL",
      "country": "India"
    },
    {
      "fn": "G9 688",
      "airline": "AIR ARABIA",
      "status": "",
      "pax": 180,
      "aircraft": "321",
      "dep_time": "2026-05-04T01:45",
      "arr_time": "2026-05-04T05:55",
      "to": "SHJ",
      "country": "UAE"
    },
    {
      "fn": "EY 415",
      "airline": "ETIHAD AIRWAYS",
      "status": "",
      "pax": 237,
      "aircraft": "789",
      "dep_time": "2026-05-04T01:50",
      "arr_time": "2026-05-04T05:30",
      "to": "AUH",
      "country": "UAE"
    },
    {
      "fn": "9C 8668",
      "airline": "SPRING AIRLINES LIMITED CORPORATION",
      "status": "cancelled",
      "pax": 147,
      "aircraft": "320",
      "dep_time": "2026-05-04T01:55",
      "arr_time": "2026-05-04T08:55",
      "to": "PVG",
      "country": "China"
    },
    {
      "fn": "9C 7654",
      "airline": "SPRING AIRLINES LIMITED CORPORATION",
      "status": "",
      "pax": 147,
      "aircraft": "320",
      "dep_time": "2026-05-04T02:05",
      "arr_time": "2026-05-04T07:15",
      "to": "TFU",
      "country": ""
    },
    {
      "fn": "WY 834",
      "airline": "OMAN AIR",
      "status": "",
      "pax": 147,
      "aircraft": "7M8",
      "dep_time": "2026-05-04T02:10",
      "arr_time": "2026-05-04T05:25",
      "to": "MCT",
      "country": "Oman"
    },
    {
      "fn": "QR 843",
      "airline": "QATAR AIRWAYS COMPANY",
      "status": "cancelled",
      "pax": 324,
      "aircraft": "77W",
      "dep_time": "2026-05-04T02:20",
      "arr_time": "2026-05-04T04:20",
      "to": "DOH",
      "country": "Qatar"
    },
    {
      "fn": "TR 659",
      "airline": "SCOOT PTE LTD",
      "status": "",
      "pax": 147,
      "aircraft": "",
      "dep_time": "2026-05-04T02:20",
      "arr_time": "2026-05-04T05:45",
      "to": "SIN",
      "country": "Singapore"
    },
    {
      "fn": "EY 411",
      "airline": "ETIHAD AIRWAYS",
      "status": "",
      "pax": 147,
      "aircraft": "",
      "dep_time": "2026-05-04T02:25",
      "arr_time": "2026-05-04T05:45",
      "to": "AUH",
      "country": "UAE"
    },
    {
      "fn": "SQ 725",
      "airline": "SINGAPORE AIRLINES LIMITED",
      "status": "",
      "pax": 147,
      "aircraft": "7M8",
      "dep_time": "2026-05-04T02:25",
      "arr_time": "2026-05-04T06:00",
      "to": "SIN",
      "country": "Singapore"
    },
    {
      "fn": "EK 391",
      "airline": "EMIRATES",
      "status": "cancelled",
      "pax": 324,
      "aircraft": "77W",
      "dep_time": "2026-05-04T03:00",
      "arr_time": "",
      "to": "DXB",
      "country": "UAE"
    },
    {
      "fn": "MH 787",
      "airline": "MALAYSIA AIRLINES",
      "status": "",
      "pax": 154,
      "aircraft": "738",
      "dep_time": "2026-05-04T03:30",
      "arr_time": "2026-05-04T06:00",
      "to": "KUL",
      "country": "Malaysia"
    },
    {
      "fn": "KC 564",
      "airline": "AIR ASTANA",
      "status": "",
      "pax": 147,
      "aircraft": "",
      "dep_time": "2026-05-04T03:30",
      "arr_time": "2026-05-04T08:45",
      "to": "ALA",
      "country": "Kazakhstan"
    },
    {
      "fn": "SU 285",
      "airline": "AEROFLOT RUSSIAN AIRLINES",
      "status": "",
      "pax": 324,
      "aircraft": "77W",
      "dep_time": "2026-05-04T03:35",
      "arr_time": "2026-05-04T09:35",
      "to": "SVO",
      "country": "Russia"
    },
    {
      "fn": "G9 700",
      "airline": "AIR ARABIA",
      "status": "",
      "pax": 180,
      "aircraft": "321",
      "dep_time": "2026-05-04T03:45",
      "arr_time": "",
      "to": "SHJ",
      "country": "UAE"
    },
    {
      "fn": "6E 1074",
      "airline": "INTERGLOBE AVIATION LIMITED (INDIGO)",
      "status": "",
      "pax": 147,
      "aircraft": "",
      "dep_time": "2026-05-04T04:05",
      "arr_time": "2026-05-04T07:20",
      "to": "DEL",
      "country": "India"
    },
    {
      "fn": "AK 833",
      "airline": "AIRASIA BERHAD",
      "status": "",
      "pax": 147,
      "aircraft": "320",
      "dep_time": "2026-05-04T04:10",
      "arr_time": "2026-05-04T06:45",
      "to": "KUL",
      "country": "Malaysia"
    },
    {
      "fn": "UO 725",
      "airline": "HONG KONG EXPRESS AIRWAYS",
      "status": "",
      "pax": 147,
      "aircraft": "",
      "dep_time": "2026-05-04T04:15",
      "arr_time": "2026-05-04T09:00",
      "to": "HKG",
      "country": "Hong Kong"
    },
    {
      "fn": "WK 051",
      "airline": "EDELWEISS AIR AG",
      "status": "",
      "pax": 266,
      "aircraft": "359",
      "dep_time": "2026-05-04T04:35",
      "arr_time": "2026-05-04T11:55",
      "to": "ZRH",
      "country": "Switzerland"
    },
    {
      "fn": "SQ 727",
      "airline": "SINGAPORE AIRLINES LIMITED",
      "status": "",
      "pax": 147,
      "aircraft": "7M8",
      "dep_time": "2026-05-04T04:40",
      "arr_time": "2026-05-04T07:55",
      "to": "SIN",
      "country": "Singapore"
    },
    {
      "fn": "CX 770",
      "airline": "CATHAY PACIFIC AIRWAYS",
      "status": "",
      "pax": 147,
      "aircraft": "",
      "dep_time": "2026-05-04T04:50",
      "arr_time": "2026-05-04T09:50",
      "to": "HKG",
      "country": "Hong Kong"
    },
    {
      "fn": "VJ 808",
      "airline": "VIETJET AIR",
      "status": "",
      "pax": 147,
      "aircraft": "320",
      "dep_time": "2026-05-04T04:55",
      "arr_time": "2026-05-04T06:50",
      "to": "SGN",
      "country": "Vietnam"
    },
    {
      "fn": "6E 1072",
      "airline": "INTERGLOBE AVIATION LIMITED (INDIGO)",
      "status": "",
      "pax": 147,
      "aircraft": "",
      "dep_time": "2026-05-04T05:20",
      "arr_time": "2026-05-04T08:10",
      "to": "BOM",
      "country": "India"
    },
    {
      "fn": "6E 1088",
      "airline": "INTERGLOBE AVIATION LIMITED (INDIGO)",
      "status": "",
      "pax": 147,
      "aircraft": "",
      "dep_time": "2026-05-04T05:25",
      "arr_time": "2026-05-04T06:55",
      "to": "CCU",
      "country": "India"
    },
    {
      "fn": "SU 627",
      "airline": "AEROFLOT RUSSIAN AIRLINES",
      "status": "",
      "pax": 262,
      "aircraft": "333",
      "dep_time": "2026-05-04T05:35",
      "arr_time": "2026-05-04T12:45",
      "to": "SVX",
      "country": "Russia"
    },
    {
      "fn": "6E 1076",
      "airline": "INTERGLOBE AVIATION LIMITED (INDIGO)",
      "status": "",
      "pax": 147,
      "aircraft": "",
      "dep_time": "2026-05-04T05:45",
      "arr_time": "2026-05-04T07:40",
      "to": "BLR",
      "country": "India"
    },
    {
      "fn": "TR 657",
      "airline": "SCOOT PTE LTD",
      "status": "",
      "pax": 147,
      "aircraft": "",
      "dep_time": "2026-05-04T06:15",
      "arr_time": "2026-05-04T09:35",
      "to": "SIN",
      "country": "Singapore"
    },
    {
      "fn": "SU 635",
      "airline": "AEROFLOT RUSSIAN AIRLINES",
      "status": "",
      "pax": 324,
      "aircraft": "77W",
      "dep_time": "2026-05-04T06:25",
      "arr_time": "",
      "to": "KJA",
      "country": "Russia"
    },
    {
      "fn": "OD 541",
      "airline": "MALINDO AIRWAYS SDN BHD",
      "status": "",
      "pax": 154,
      "aircraft": "738",
      "dep_time": "2026-05-04T06:30",
      "arr_time": "",
      "to": "KUL",
      "country": "Malaysia"
    },
    {
      "fn": "AK 825",
      "airline": "AIRASIA BERHAD",
      "status": "",
      "pax": 147,
      "aircraft": "320",
      "dep_time": "2026-05-04T06:35",
      "arr_time": "2026-05-04T09:10",
      "to": "KUL",
      "country": "Malaysia"
    },
    {
      "fn": "9C 8670",
      "airline": "SPRING AIRLINES LIMITED CORPORATION",
      "status": "cancelled",
      "pax": 147,
      "aircraft": "320",
      "dep_time": "2026-05-04T06:40",
      "arr_time": "",
      "to": "PVG",
      "country": "China"
    },
    {
      "fn": "QP 619",
      "airline": "AKASA AIR",
      "status": "",
      "pax": 147,
      "aircraft": "7M8",
      "dep_time": "2026-05-04T06:50",
      "arr_time": "2026-05-04T13:15",
      "to": "BOM",
      "country": "India"
    },
    {
      "fn": "CA 414",
      "airline": "AIR CHINA",
      "status": "",
      "pax": 147,
      "aircraft": "",
      "dep_time": "2026-05-04T07:00",
      "arr_time": "2026-05-04T12:05",
      "to": "TFU",
      "country": ""
    },
    {
      "fn": "MH 795",
      "airline": "MALAYSIA AIRLINES",
      "status": "",
      "pax": 154,
      "aircraft": "738",
      "dep_time": "2026-05-04T07:05",
      "arr_time": "2026-05-04T12:30",
      "to": "KUL",
      "country": "Malaysia"
    },
    {
      "fn": "FY 3601",
      "airline": "FLYFIREFLY SDN BHD",
      "status": "",
      "pax": 154,
      "aircraft": "738",
      "dep_time": "2026-05-04T07:35",
      "arr_time": "2026-05-04T09:35",
      "to": "PEN",
      "country": "Malaysia"
    },
    {
      "fn": "AK 1821",
      "airline": "AIRASIA BERHAD",
      "status": "",
      "pax": 147,
      "aircraft": "320",
      "dep_time": "2026-05-04T07:55",
      "arr_time": "",
      "to": "PEN",
      "country": "Malaysia"
    },
    {
      "fn": "SQ 731",
      "airline": "SINGAPORE AIRLINES LIMITED",
      "status": "",
      "pax": 147,
      "aircraft": "7M8",
      "dep_time": "2026-05-04T08:00",
      "arr_time": "2026-05-04T10:55",
      "to": "SIN",
      "country": "Singapore"
    },
    {
      "fn": "QR 840",
      "airline": "QATAR AIRWAYS COMPANY",
      "status": "cancelled",
      "pax": 324,
      "aircraft": "77W",
      "dep_time": "2026-05-04T08:35",
      "arr_time": "2026-05-04T11:00",
      "to": "PEN",
      "country": "Malaysia"
    },
    {
      "fn": "9C 8758",
      "airline": "SPRING AIRLINES LIMITED CORPORATION",
      "status": "cancelled",
      "pax": 147,
      "aircraft": "320",
      "dep_time": "2026-05-04T08:35",
      "arr_time": "2026-05-04T20:35",
      "to": "TFU",
      "country": ""
    },
    {
      "fn": "AK 823",
      "airline": "AIRASIA BERHAD",
      "status": "",
      "pax": 147,
      "aircraft": "320",
      "dep_time": "2026-05-04T09:00",
      "arr_time": "2026-05-04T11:10",
      "to": "KUL",
      "country": "Malaysia"
    },
    {
      "fn": "QP 624",
      "airline": "AKASA AIR",
      "status": "",
      "pax": 147,
      "aircraft": "7M8",
      "dep_time": "2026-05-04T09:10",
      "arr_time": "2026-05-04T12:55",
      "to": "BLR",
      "country": "India"
    },
    {
      "fn": "CZ 6064",
      "airline": "CHINA SOUTHERN AIRLINES",
      "status": "",
      "pax": 147,
      "aircraft": "320",
      "dep_time": "2026-05-04T09:40",
      "arr_time": "2026-05-04T14:55",
      "to": "CAN",
      "country": "China"
    },
    {
      "fn": "IX 937",
      "airline": "AIR INDIA EXPRESS",
      "status": "",
      "pax": 147,
      "aircraft": "7M8",
      "dep_time": "2026-05-04T09:45",
      "arr_time": "2026-05-04T07:55",
      "to": "HYD",
      "country": "India"
    },
    {
      "fn": "AK 821",
      "airline": "AIRASIA BERHAD",
      "status": "",
      "pax": 147,
      "aircraft": "320",
      "dep_time": "2026-05-04T10:05",
      "arr_time": "2026-05-04T12:25",
      "to": "KUL",
      "country": "Malaysia"
    },
    {
      "fn": "AK 1317",
      "airline": "AIRASIA BERHAD",
      "status": "cancelled",
      "pax": 147,
      "aircraft": "320",
      "dep_time": "2026-05-04T10:15",
      "arr_time": "",
      "to": "JHB",
      "country": ""
    },
    {
      "fn": "SQ 735",
      "airline": "SINGAPORE AIRLINES LIMITED",
      "status": "",
      "pax": 147,
      "aircraft": "7M8",
      "dep_time": "2026-05-04T11:00",
      "arr_time": "2026-05-04T14:00",
      "to": "SIN",
      "country": "Singapore"
    },
    {
      "fn": "MH 791",
      "airline": "MALAYSIA AIRLINES",
      "status": "",
      "pax": 154,
      "aircraft": "738",
      "dep_time": "2026-05-04T11:05",
      "arr_time": "2026-05-04T13:55",
      "to": "KUL",
      "country": "Malaysia"
    },
    {
      "fn": "CX 778",
      "airline": "CATHAY PACIFIC AIRWAYS",
      "status": "",
      "pax": 262,
      "aircraft": "333",
      "dep_time": "2026-05-04T11:20",
      "arr_time": "2026-05-04T16:15",
      "to": "HKG",
      "country": "Hong Kong"
    },
    {
      "fn": "G9 715",
      "airline": "AIR ARABIA",
      "status": "",
      "pax": 180,
      "aircraft": "321",
      "dep_time": "2026-05-04T11:40",
      "arr_time": "2026-05-04T15:05",
      "to": "SHJ",
      "country": "UAE"
    },
    {
      "fn": "VN 620",
      "airline": "VIETNAM AIRLINES",
      "status": "cancelled",
      "pax": 180,
      "aircraft": "321",
      "dep_time": "2026-05-04T11:45",
      "arr_time": "",
      "to": "SGN",
      "country": "Vietnam"
    },
    {
      "fn": "3U 3932",
      "airline": "SICHUAN AIRLINES",
      "status": "",
      "pax": 180,
      "aircraft": "321",
      "dep_time": "2026-05-04T12:05",
      "arr_time": "2026-05-04T16:25",
      "to": "TFU",
      "country": ""
    },
    {
      "fn": "CA 822",
      "airline": "AIR CHINA",
      "status": "",
      "pax": 147,
      "aircraft": "7M8",
      "dep_time": "2026-05-04T12:25",
      "arr_time": "2026-05-04T17:50",
      "to": "PEK",
      "country": "China"
    },
    {
      "fn": "HX 742",
      "airline": "HONG KONG AIRLINES LTD",
      "status": "",
      "pax": 147,
      "aircraft": "320",
      "dep_time": "2026-05-04T12:35",
      "arr_time": "2026-05-04T13:20",
      "to": "HKG",
      "country": "Hong Kong"
    },
    {
      "fn": "QZ 247",
      "airline": "INDONESIA AIRASIA PT.",
      "status": "",
      "pax": 147,
      "aircraft": "320",
      "dep_time": "2026-05-04T12:40",
      "arr_time": "2026-05-04T17:30",
      "to": "DPS",
      "country": "Indonesia"
    },
    {
      "fn": "EK 379",
      "airline": "EMIRATES",
      "status": "",
      "pax": 324,
      "aircraft": "77W",
      "dep_time": "2026-05-04T12:55",
      "arr_time": "2026-05-04T15:40",
      "to": "DXB",
      "country": "UAE"
    },
    {
      "fn": "SQ 739",
      "airline": "SINGAPORE AIRLINES LIMITED",
      "status": "",
      "pax": 147,
      "aircraft": "7M8",
      "dep_time": "2026-05-04T13:10",
      "arr_time": "2026-05-04T16:25",
      "to": "SIN",
      "country": "Singapore"
    },
    {
      "fn": "QR 847",
      "airline": "QATAR AIRWAYS COMPANY",
      "status": "cancelled",
      "pax": 324,
      "aircraft": "77W",
      "dep_time": "2026-05-04T13:30",
      "arr_time": "2026-05-04T16:30",
      "to": "DOH",
      "country": "Qatar"
    },
    {
      "fn": "N4 3516",
      "airline": "NORDWIND AIRLINES",
      "status": "",
      "pax": 262,
      "aircraft": "333",
      "dep_time": "2026-05-04T13:35",
      "arr_time": "",
      "to": "OVB",
      "country": "Russia"
    },
    {
      "fn": "9C 8772",
      "airline": "SPRING AIRLINES LIMITED CORPORATION",
      "status": "cancelled",
      "pax": 147,
      "aircraft": "320",
      "dep_time": "2026-05-04T13:45",
      "arr_time": "2026-05-04T20:15",
      "to": "CAN",
      "country": "China"
    },
    {
      "fn": "EY 417",
      "airline": "ETIHAD AIRWAYS",
      "status": "",
      "pax": 147,
      "aircraft": "",
      "dep_time": "2026-05-04T13:45",
      "arr_time": "",
      "to": "AUH",
      "country": "UAE"
    },
    {
      "fn": "WY 832",
      "airline": "OMAN AIR",
      "status": "",
      "pax": 147,
      "aircraft": "7M8",
      "dep_time": "2026-05-04T13:50",
      "arr_time": "2026-05-04T15:40",
      "to": "MCT",
      "country": "Oman"
    },
    {
      "fn": "TR 653",
      "airline": "SCOOT PTE LTD",
      "status": "",
      "pax": 147,
      "aircraft": "",
      "dep_time": "2026-05-04T13:50",
      "arr_time": "2026-05-04T16:15",
      "to": "SIN",
      "country": "Singapore"
    },
    {
      "fn": "QR 841",
      "airline": "QATAR AIRWAYS COMPANY",
      "status": "",
      "pax": 324,
      "aircraft": "77W",
      "dep_time": "2026-05-04T14:00",
      "arr_time": "2026-05-04T20:50",
      "to": "DOH",
      "country": "Qatar"
    },
    {
      "fn": "JQ 028",
      "airline": "JETSTAR AIRWAYS PTY LIMITED",
      "status": "",
      "pax": 205,
      "aircraft": "788",
      "dep_time": "2026-05-04T14:05",
      "arr_time": "2026-05-05T02:40",
      "to": "SYD",
      "country": "Australia"
    },
    {
      "fn": "OD 543",
      "airline": "MALINDO AIRWAYS SDN BHD",
      "status": "cancelled",
      "pax": 147,
      "aircraft": "7M8",
      "dep_time": "2026-05-04T14:10",
      "arr_time": "",
      "to": "KUL",
      "country": "Malaysia"
    },
    {
      "fn": "EY 413",
      "airline": "ETIHAD AIRWAYS",
      "status": "",
      "pax": 147,
      "aircraft": "",
      "dep_time": "2026-05-04T14:20",
      "arr_time": "2026-05-04T17:35",
      "to": "AUH",
      "country": "UAE"
    },
    {
      "fn": "9C 8774",
      "airline": "SPRING AIRLINES LIMITED CORPORATION",
      "status": "",
      "pax": 147,
      "aircraft": "320",
      "dep_time": "2026-05-04T14:30",
      "arr_time": "",
      "to": "CAN",
      "country": "China"
    },
    {
      "fn": "9C 8666",
      "airline": "SPRING AIRLINES LIMITED CORPORATION",
      "status": "",
      "pax": 147,
      "aircraft": "320",
      "dep_time": "2026-05-04T14:45",
      "arr_time": "",
      "to": "PVG",
      "country": "China"
    },
    {
      "fn": "CA 552",
      "airline": "AIR CHINA",
      "status": "",
      "pax": 147,
      "aircraft": "7M8",
      "dep_time": "2026-05-04T15:15",
      "arr_time": "",
      "to": "PEK",
      "country": "China"
    },
    {
      "fn": "AI 2377",
      "airline": "AIR INDIA LTD",
      "status": "",
      "pax": 147,
      "aircraft": "",
      "dep_time": "2026-05-04T15:20",
      "arr_time": "2026-05-04T18:45",
      "to": "DEL",
      "country": "India"
    },
    {
      "fn": "TK 173",
      "airline": "TURK HAVA YOLLARI (TURKISH AIRLINES CO.)",
      "status": "",
      "pax": 262,
      "aircraft": "333",
      "dep_time": "2026-05-04T15:35",
      "arr_time": "2026-05-04T22:30",
      "to": "IST",
      "country": "Turkey"
    },
    {
      "fn": "6E 1082",
      "airline": "INTERGLOBE AVIATION LIMITED (INDIGO)",
      "status": "",
      "pax": 147,
      "aircraft": "",
      "dep_time": "2026-05-04T15:50",
      "arr_time": "2026-05-04T18:35",
      "to": "DEL",
      "country": "India"
    },
    {
      "fn": "OZ 748",
      "airline": "ASIANA AIRLINES",
      "status": "",
      "pax": 262,
      "aircraft": "333",
      "dep_time": "2026-05-04T15:50",
      "arr_time": "2026-05-05T00:15",
      "to": "ICN",
      "country": "South Korea"
    },
    {
      "fn": "6E 1090",
      "airline": "INTERGLOBE AVIATION LIMITED (INDIGO)",
      "status": "",
      "pax": 147,
      "aircraft": "",
      "dep_time": "2026-05-04T15:55",
      "arr_time": "2026-05-04T18:50",
      "to": "BOM",
      "country": "India"
    },
    {
      "fn": "JQ 070",
      "airline": "JETSTAR AIRWAYS PTY LIMITED",
      "status": "cancelled",
      "pax": 147,
      "aircraft": "",
      "dep_time": "2026-05-04T16:00",
      "arr_time": "",
      "to": "PER",
      "country": "Australia"
    },
    {
      "fn": "FM 858",
      "airline": "SHANGHAI AIRLINES",
      "status": "",
      "pax": 147,
      "aircraft": "7M8",
      "dep_time": "2026-05-04T16:05",
      "arr_time": "2026-05-04T22:00",
      "to": "PVG",
      "country": "China"
    },
    {
      "fn": "HB 271",
      "airline": "GREATER BAY AIRLINES",
      "status": "",
      "pax": 154,
      "aircraft": "738",
      "dep_time": "2026-05-04T16:10",
      "arr_time": "",
      "to": "HKG",
      "country": "Hong Kong"
    },
    {
      "fn": "9C 8782",
      "airline": "SPRING AIRLINES LIMITED CORPORATION",
      "status": "",
      "pax": 147,
      "aircraft": "320",
      "dep_time": "2026-05-04T16:20",
      "arr_time": "",
      "to": "SZX",
      "country": "China"
    },
    {
      "fn": "KE 678",
      "airline": "KOREAN AIRLINES CO.LTD.",
      "status": "",
      "pax": 237,
      "aircraft": "789",
      "dep_time": "2026-05-04T16:25",
      "arr_time": "2026-05-05T00:35",
      "to": "ICN",
      "country": "South Korea"
    },
    {
      "fn": "CZ 6058",
      "airline": "CHINA SOUTHERN AIRLINES",
      "status": "",
      "pax": 147,
      "aircraft": "",
      "dep_time": "2026-05-04T16:35",
      "arr_time": "2026-05-04T20:35",
      "to": "CAN",
      "country": "China"
    },
    {
      "fn": "9C 8522",
      "airline": "SPRING AIRLINES LIMITED CORPORATION",
      "status": "",
      "pax": 147,
      "aircraft": "320",
      "dep_time": "2026-05-04T16:35",
      "arr_time": "",
      "to": "PVG",
      "country": "China"
    },
    {
      "fn": "EK 397",
      "airline": "EMIRATES",
      "status": "",
      "pax": 324,
      "aircraft": "77W",
      "dep_time": "2026-05-04T16:45",
      "arr_time": "2026-05-04T20:25",
      "to": "DXB",
      "country": "UAE"
    },
    {
      "fn": "FD 192",
      "airline": "THAI AIR ASIA CO.LTD.",
      "status": "cancelled",
      "pax": 147,
      "aircraft": "320",
      "dep_time": "2026-05-04T16:50",
      "arr_time": "",
      "to": "MAA",
      "country": "India"
    },
    {
      "fn": "SV 853",
      "airline": "SAUDI ARABIAN AIRLINES",
      "status": "cancelled",
      "pax": 237,
      "aircraft": "789",
      "dep_time": "2026-05-04T17:00",
      "arr_time": "2026-05-04T21:55",
      "to": "JED",
      "country": "Saudi Arabia"
    }
  ]
}